aws_healthchecker_response/__init__.py
aws_healthchecker_response/middleware.py
aws_healthchecker_response-0.2.1.dist-info/LICENSE
aws_healthchecker_response-0.2.1.dist-info/WHEEL
aws_healthchecker_response-0.2.1.dist-info/METADATA
aws_healthchecker_response-0.2.1.dist-info/RECORD
